moddb/__init__.py
moddb/base.py
moddb/boxes.py
moddb/client.py
moddb/enums.py
moddb/errors.py
moddb/utils.py
moddb/pages/__init__.py
moddb/pages/article.py
moddb/pages/base.py
moddb/pages/engine.py
moddb/pages/entity.py
moddb/pages/file.py
moddb/pages/fp.py
moddb/pages/game.py
moddb/pages/job.py
moddb/pages/mixins.py
moddb/pages/mod.py
moddb/pages/opinion.py
moddb/pages/platform.py
moddb/pages/ware.py
moddb-0.14.0.dist-info/licenses/LICENSE
moddb-0.14.0.dist-info/METADATA
moddb-0.14.0.dist-info/WHEEL
moddb-0.14.0.dist-info/top_level.txt
moddb-0.14.0.dist-info/RECORD
