Metadata-Version: 2.4
Name: moddb
Version: 0.14.0
Summary: A scrapper for ModDB Mod and Game pages
Home-page: https://github.com/ClementJ18/moddb
Author: Clement Julia
Author-email: clement.julia13@gmail.com
License-File: LICENSE
Requires-Dist: beautifulsoup4==4.*
Requires-Dist: requests==2.*
Requires-Dist: curl_adapter==1.*
Dynamic: author
Dynamic: author-email
Dynamic: description
Dynamic: description-content-type
Dynamic: home-page
Dynamic: license-file
Dynamic: requires-dist
Dynamic: summary
